basil/__init__.py
basil/__pycache__/__init__.cpython-311.pyc
basil/__pycache__/error_collector.cpython-311.pyc
basil/__pycache__/exceptions.cpython-311.pyc
basil/__pycache__/file_parser.cpython-311.pyc
basil/__pycache__/models.cpython-311.pyc
basil/__pycache__/parser.cpython-311.pyc
basil/__pycache__/syntax_loader.cpython-311.pyc
basil/error_collector.py
basil/exceptions.py
basil/file_parser.py
basil/models.py
basil/parser.py
basil/py.typed
basil/syntax_loader/__init__.py
basil/syntax_loader/__pycache__/__init__.cpython-311.pyc
basil/syntax_loader/__pycache__/exceptions.cpython-311.pyc
basil/syntax_loader/__pycache__/syntax_loader.cpython-311.pyc
basil/syntax_loader/exceptions.py
basil/syntax_loader/syntax_loader.py
basil_parser-0.4.3.dist-info/METADATA
basil_parser-0.4.3.dist-info/WHEEL
basil_parser-0.4.3.dist-info/licenses/LICENSE.md
basil_parser-0.4.3.dist-info/RECORD
