Metadata-Version: 2.1
Name: basil-parser
Version: 0.4.3
Summary: Parser library using JSON file to describe language.
Author-Email: Luuk Verweij <luuk_verweij@msn.com>
License: MIT
Requires-Python: >=3.11
